sorting_algos/__init__.py
sorting_algos/sorting_algos.py
soroush_sorting_algos-0.0.2.dist-info/METADATA
soroush_sorting_algos-0.0.2.dist-info/WHEEL
soroush_sorting_algos-0.0.2.dist-info/top_level.txt
soroush_sorting_algos-0.0.2.dist-info/RECORD
