Metadata-Version: 2.4
Name: soroush_sorting_algos
Version: 0.0.2
Summary: Sorting Algorithms
Author: Soroush
Author-email: sorooshjaberi@gmail.com
Dynamic: author
Dynamic: author-email
Dynamic: summary
